2fa
setup.py
2fa.egg-info/PKG-INFO
2fa.egg-info/SOURCES.txt
2fa.egg-info/dependency_links.txt
2fa.egg-info/requires.txt
2fa.egg-info/top_level.txt
pyotp/__init__.py
pyotp/hotp.py
pyotp/otp.py
pyotp/totp.py
pyotp/utils.py