Metadata-Version: 1.1
Name: 2fa
Version: 0.0.1
Summary: A command-line 2-factor authentication manager
Home-page: https://github.com/seiyanuta/2fa
Author: UNKNOWN
Author-email: UNKNOWN
License: UNKNOWN
Platform: UNKNOWN
Classifier: Operating System :: POSIX
Classifier: Environment :: Console
Classifier: Topic :: Utilities
